filebundler/FileBundlerApp.py
filebundler/__init__.py
filebundler/_version.py
filebundler/app.py
filebundler/constants.py
filebundler/main.py
filebundler/mcp_server.py
filebundler/state.py
filebundler/features/sort_files.py
filebundler/features/ignore_patterns/__init__.py
filebundler/features/ignore_patterns/default-ignore-patterns.txt
filebundler/features/tasks/__init__.py
filebundler/features/tasks/templates/example-task.md
filebundler/features/tasks/templates/task-file-management.md
filebundler/lib/llm/auto_bundle.py
filebundler/lib/llm/claude.py
filebundler/lib/llm/gemini.py
filebundler/lib/llm/registry.py
filebundler/managers/BundleManager.py
filebundler/managers/GlobalSettingsManager.py
filebundler/managers/ProjectSettingsManager.py
filebundler/managers/SelectionsManager.py
filebundler/models/AppProtocol.py
filebundler/models/Bundle.py
filebundler/models/BundleMetadata.py
filebundler/models/FileItem.py
filebundler/models/GlobalSettings.py
filebundler/models/ProjectSettings.py
filebundler/models/llm/AutoBundleResponse.py
filebundler/services/cli_chat_instruction.py
filebundler/services/cli_unbundle.py
filebundler/services/code_export_service.py
filebundler/services/project_structure.py
filebundler/services/token_count.py
filebundler/ui/confirm.py
filebundler/ui/notification.py
filebundler/ui/components/selectable_file_items.py
filebundler/ui/sidebar/file_tree.py
filebundler/ui/sidebar/file_tree_buttons.py
filebundler/ui/sidebar/project_selection.py
filebundler/ui/sidebar/settings_panel.py
filebundler/ui/tabs/debug.py
filebundler/ui/tabs/export_contents.py
filebundler/ui/tabs/global_settings_panel.py
filebundler/ui/tabs/manage_bundles.py
filebundler/ui/tabs/selected_files.py
filebundler/ui/tabs/auto_bundler/before_submit.py
filebundler/ui/tabs/auto_bundler/render_auto_bundler.py
filebundler/utils/__init__.py
filebundler/utils/filepath_checker.py
filebundler/utils/language_formatting.py
filebundler-0.9.19.dist-info/METADATA
filebundler-0.9.19.dist-info/WHEEL
filebundler-0.9.19.dist-info/entry_points.txt
filebundler-0.9.19.dist-info/licenses/LICENSE
filebundler-0.9.19.dist-info/RECORD
