Metadata-Version: 2.4
Name: filebundler
Version: 0.9.19
Summary: File Bundler is an app to bundle project files together and use them for LLM prompting. It helps estimate and optimize token and context usage.
Project-URL: Homepage, https://github.com/dsfaccini/filebundler
Project-URL: Issues, https://github.com/dsfaccini/filebundler/issues
Author-email: DavidSF <david@filebundler.com>
License-Expression: GPL-3.0-or-later
License-File: LICENSE
Classifier: Development Status :: 4 - Beta
Classifier: Intended Audience :: Developers
Classifier: License :: OSI Approved :: GNU General Public License v3 or later (GPLv3+)
Classifier: Programming Language :: Python :: 3
Classifier: Programming Language :: Python :: 3.12
Classifier: Topic :: Software Development :: Libraries
Classifier: Topic :: Utilities
Requires-Python: >=3.12
Requires-Dist: logfire>=3.9.0
Requires-Dist: pydantic-ai-slim[anthropic]>=0.0.42
Requires-Dist: pydantic-ai[logfire]>=0.0.42
Requires-Dist: pydantic-settings>=2.8.1
Requires-Dist: pydantic>=2.10.6
Requires-Dist: pyperclip>=1.9.0
Requires-Dist: streamlit>=1.43.2
Requires-Dist: tiktoken>=0.9.0
